[
	{
		"id": 174852,
		"imageUrl": "http://gatherer.wizards.com/Handlers/Image.ashx?multiverseid=174852&type=card",
		"name": "Ajani Vengeant"
	},
	{
		"id": 174852,
		"imageUrl": "http://gatherer.wizards.com/Handlers/Image.ashx?multiverseid=174852&type=card",
		"name": "Ajani Vengeant"
	},
	{
		"id": 373521,
		"imageUrl": "http://gatherer.wizards.com/Handlers/Image.ashx?multiverseid=373521&type=card",
		"name": "Chained to the Rocks"
	},
	{
		"id": 373521,
		"imageUrl": "http://gatherer.wizards.com/Handlers/Image.ashx?multiverseid=373521&type=card",
		"name": "Chained to the Rocks"
	},
	{
		"id": 373521,
		"imageUrl": "http://gatherer.wizards.com/Handlers/Image.ashx?multiverseid=373521&type=card",
		"name": "Chained to the Rocks"
	},
	{
		"id": 386516,
		"imageUrl": "http://gatherer.wizards.com/Handlers/Image.ashx?multiverseid=386516&type=card",
		"name": "Deflecting Palm"
	},
	{
		"id": 386516,
		"imageUrl": "http://gatherer.wizards.com/Handlers/Image.ashx?multiverseid=386516&type=card",
		"name": "Deflecting Palm"
	},
	{
		"id": 386516,
		"imageUrl": "http://gatherer.wizards.com/Handlers/Image.ashx?multiverseid=386516&type=card",
		"name": "Deflecting Palm"
	},
	{
		"id": 240072,
		"imageUrl": "http://gatherer.wizards.com/Handlers/Image.ashx?multiverseid=240072&type=card",
		"name": "Divine Deflection"
	},
	{
		"id": 240072,
		"imageUrl": "http://gatherer.wizards.com/Handlers/Image.ashx?multiverseid=240072&type=card",
		"name": "Divine Deflection"
	},
	{
		"id": 240072,
		"imageUrl": "http://gatherer.wizards.com/Handlers/Image.ashx?multiverseid=240072&type=card",
		"name": "Divine Deflection"
	},
	{
		"id": 366385,
		"imageUrl": "http://gatherer.wizards.com/Handlers/Image.ashx?multiverseid=366385&type=card",
		"name": "Boros Reckoner"
	},
	{
		"id": 366385,
		"imageUrl": "http://gatherer.wizards.com/Handlers/Image.ashx?multiverseid=366385&type=card",
		"name": "Boros Reckoner"
	},
	{
		"id": 366385,
		"imageUrl": "http://gatherer.wizards.com/Handlers/Image.ashx?multiverseid=366385&type=card",
		"name": "Boros Reckoner"
	},
	{
		"id": 366385,
		"imageUrl": "http://gatherer.wizards.com/Handlers/Image.ashx?multiverseid=366385&type=card",
		"name": "Boros Reckoner"
	},
	{
		"id": 194208,
		"imageUrl": "http://gatherer.wizards.com/Handlers/Image.ashx?multiverseid=194208&type=card",
		"name": "Apostle's Blessing"
	},
	{
		"id": 194208,
		"imageUrl": "http://gatherer.wizards.com/Handlers/Image.ashx?multiverseid=194208&type=card",
		"name": "Apostle's Blessing"
	},
	{
		"id": 366435,
		"imageUrl": "http://gatherer.wizards.com/Handlers/Image.ashx?multiverseid=366435&type=card",
		"name": "Boros Charm"
	},
	{
		"id": 366435,
		"imageUrl": "http://gatherer.wizards.com/Handlers/Image.ashx?multiverseid=366435&type=card",
		"name": "Boros Charm"
	},
	{
		"id": 366435,
		"imageUrl": "http://gatherer.wizards.com/Handlers/Image.ashx?multiverseid=366435&type=card",
		"name": "Boros Charm"
	},
	{
		"id": 366435,
		"imageUrl": "http://gatherer.wizards.com/Handlers/Image.ashx?multiverseid=366435&type=card",
		"name": "Boros Charm"
	},
	{
		"id": 222206,
		"imageUrl": "http://gatherer.wizards.com/Handlers/Image.ashx?multiverseid=222206&type=card",
		"name": "Blasphemous Act"
	},
	{
		"id": 222206,
		"imageUrl": "http://gatherer.wizards.com/Handlers/Image.ashx?multiverseid=222206&type=card",
		"name": "Blasphemous Act"
	},
	{
		"id": 222206,
		"imageUrl": "http://gatherer.wizards.com/Handlers/Image.ashx?multiverseid=222206&type=card",
		"name": "Blasphemous Act"
	},
	{
		"id": 89066,
		"imageUrl": "http://gatherer.wizards.com/Handlers/Image.ashx?multiverseid=89066&type=card",
		"name": "Sacred Foundry"
	},
	{
		"id": 89066,
		"imageUrl": "http://gatherer.wizards.com/Handlers/Image.ashx?multiverseid=89066&type=card",
		"name": "Sacred Foundry"
	},
	{
		"id": 89066,
		"imageUrl": "http://gatherer.wizards.com/Handlers/Image.ashx?multiverseid=89066&type=card",
		"name": "Sacred Foundry"
	},
	{
		"id": 89066,
		"imageUrl": "http://gatherer.wizards.com/Handlers/Image.ashx?multiverseid=89066&type=card",
		"name": "Sacred Foundry"
	},
	{
		"id": 124080,
		"imageUrl": "http://gatherer.wizards.com/Handlers/Image.ashx?multiverseid=124080&type=card",
		"name": "Dawn Charm"
	},
	{
		"id": 124080,
		"imageUrl": "http://gatherer.wizards.com/Handlers/Image.ashx?multiverseid=124080&type=card",
		"name": "Dawn Charm"
	},
	{
		"id": 124080,
		"imageUrl": "http://gatherer.wizards.com/Handlers/Image.ashx?multiverseid=124080&type=card",
		"name": "Dawn Charm"
	},
	{
		"id": 217992,
		"imageUrl": "http://gatherer.wizards.com/Handlers/Image.ashx?multiverseid=217992&type=card",
		"name": "Spellskite"
	},
	{
		"id": 217992,
		"imageUrl": "http://gatherer.wizards.com/Handlers/Image.ashx?multiverseid=217992&type=card",
		"name": "Spellskite"
	},
	{
		"id": 217992,
		"imageUrl": "http://gatherer.wizards.com/Handlers/Image.ashx?multiverseid=217992&type=card",
		"name": "Spellskite"
	},
	{
		"id": 89117,
		"imageUrl": "http://gatherer.wizards.com/Handlers/Image.ashx?multiverseid=89117&type=card",
		"name": "Searing Meditation"
	},
	{
		"id": 89117,
		"imageUrl": "http://gatherer.wizards.com/Handlers/Image.ashx?multiverseid=89117&type=card",
		"name": "Searing Meditation"
	},
	{
		"id": 20173,
		"imageUrl": "http://gatherer.wizards.com/Handlers/Image.ashx?multiverseid=20173&type=card",
		"name": "Story Circle"
	},
	{
		"id": 20173,
		"imageUrl": "http://gatherer.wizards.com/Handlers/Image.ashx?multiverseid=20173&type=card",
		"name": "Story Circle"
	},
	{
		"id": 20173,
		"imageUrl": "http://gatherer.wizards.com/Handlers/Image.ashx?multiverseid=20173&type=card",
		"name": "Story Circle"
	},
	{
		"id": 209,
		"imageUrl": "http://gatherer.wizards.com/Handlers/Image.ashx?multiverseid=209&type=card",
		"name": "Lightning Bolt"
	},
	{
		"id": 209,
		"imageUrl": "http://gatherer.wizards.com/Handlers/Image.ashx?multiverseid=209&type=card",
		"name": "Lightning Bolt"
	},
	{
		"id": 209,
		"imageUrl": "http://gatherer.wizards.com/Handlers/Image.ashx?multiverseid=209&type=card",
		"name": "Lightning Bolt"
	},
	{
		"id": 209,
		"imageUrl": "http://gatherer.wizards.com/Handlers/Image.ashx?multiverseid=209&type=card",
		"name": "Lightning Bolt"
	},
	{
		"id": 294,
		"imageUrl": "http://gatherer.wizards.com/Handlers/Image.ashx?multiverseid=294&type=card",
		"name": "Plains"
	},
	{
		"id": 294,
		"imageUrl": "http://gatherer.wizards.com/Handlers/Image.ashx?multiverseid=294&type=card",
		"name": "Plains"
	},
	{
		"id": 294,
		"imageUrl": "http://gatherer.wizards.com/Handlers/Image.ashx?multiverseid=294&type=card",
		"name": "Plains"
	},
	{
		"id": 294,
		"imageUrl": "http://gatherer.wizards.com/Handlers/Image.ashx?multiverseid=294&type=card",
		"name": "Plains"
	},
	{
		"id": 294,
		"imageUrl": "http://gatherer.wizards.com/Handlers/Image.ashx?multiverseid=294&type=card",
		"name": "Plains"
	},
	{
		"id": 294,
		"imageUrl": "http://gatherer.wizards.com/Handlers/Image.ashx?multiverseid=294&type=card",
		"name": "Plains"
	},
	{
		"id": 294,
		"imageUrl": "http://gatherer.wizards.com/Handlers/Image.ashx?multiverseid=294&type=card",
		"name": "Plains"
	},
	{
		"id": 294,
		"imageUrl": "http://gatherer.wizards.com/Handlers/Image.ashx?multiverseid=294&type=card",
		"name": "Plains"
	},
	{
		"id": 294,
		"imageUrl": "http://gatherer.wizards.com/Handlers/Image.ashx?multiverseid=294&type=card",
		"name": "Plains"
	},
	{
		"id": 294,
		"imageUrl": "http://gatherer.wizards.com/Handlers/Image.ashx?multiverseid=294&type=card",
		"name": "Plains"
	},
	{
		"id": 294,
		"imageUrl": "http://gatherer.wizards.com/Handlers/Image.ashx?multiverseid=294&type=card",
		"name": "Plains"
	},
	{
		"id": 87908,
		"imageUrl": "http://gatherer.wizards.com/Handlers/Image.ashx?multiverseid=87908&type=card",
		"name": "Lightning Helix"
	},
	{
		"id": 87908,
		"imageUrl": "http://gatherer.wizards.com/Handlers/Image.ashx?multiverseid=87908&type=card",
		"name": "Lightning Helix"
	},
	{
		"id": 87908,
		"imageUrl": "http://gatherer.wizards.com/Handlers/Image.ashx?multiverseid=87908&type=card",
		"name": "Lightning Helix"
	},
	{
		"id": 87908,
		"imageUrl": "http://gatherer.wizards.com/Handlers/Image.ashx?multiverseid=87908&type=card",
		"name": "Lightning Helix"
	},
	{
		"id": 179235,
		"imageUrl": "http://gatherer.wizards.com/Handlers/Image.ashx?multiverseid=179235&type=card",
		"name": "Path to Exile"
	},
	{
		"id": 179235,
		"imageUrl": "http://gatherer.wizards.com/Handlers/Image.ashx?multiverseid=179235&type=card",
		"name": "Path to Exile"
	},
	{
		"id": 179235,
		"imageUrl": "http://gatherer.wizards.com/Handlers/Image.ashx?multiverseid=179235&type=card",
		"name": "Path to Exile"
	},
	{
		"id": 391927,
		"imageUrl": "http://gatherer.wizards.com/Handlers/Image.ashx?multiverseid=391927&type=card",
		"name": "Soulfire Grand Master"
	},
	{
		"id": 391927,
		"imageUrl": "http://gatherer.wizards.com/Handlers/Image.ashx?multiverseid=391927&type=card",
		"name": "Soulfire Grand Master"
	},
	{
		"id": 391927,
		"imageUrl": "http://gatherer.wizards.com/Handlers/Image.ashx?multiverseid=391927&type=card",
		"name": "Soulfire Grand Master"
	},
	{
		"id": 391927,
		"imageUrl": "http://gatherer.wizards.com/Handlers/Image.ashx?multiverseid=391927&type=card",
		"name": "Soulfire Grand Master"
	},
	{
		"id": 158104,
		"imageUrl": "http://gatherer.wizards.com/Handlers/Image.ashx?multiverseid=158104&type=card",
		"name": "Balefire Liege"
	},
	{
		"id": 158104,
		"imageUrl": "http://gatherer.wizards.com/Handlers/Image.ashx?multiverseid=158104&type=card",
		"name": "Balefire Liege"
	},
	{
		"id": 158104,
		"imageUrl": "http://gatherer.wizards.com/Handlers/Image.ashx?multiverseid=158104&type=card",
		"name": "Balefire Liege"
	},
	{
		"id": 290,
		"imageUrl": "http://gatherer.wizards.com/Handlers/Image.ashx?multiverseid=290&type=card",
		"name": "Mountain"
	},
	{
		"id": 290,
		"imageUrl": "http://gatherer.wizards.com/Handlers/Image.ashx?multiverseid=290&type=card",
		"name": "Mountain"
	},
	{
		"id": 290,
		"imageUrl": "http://gatherer.wizards.com/Handlers/Image.ashx?multiverseid=290&type=card",
		"name": "Mountain"
	},
	{
		"id": 290,
		"imageUrl": "http://gatherer.wizards.com/Handlers/Image.ashx?multiverseid=290&type=card",
		"name": "Mountain"
	},
	{
		"id": 290,
		"imageUrl": "http://gatherer.wizards.com/Handlers/Image.ashx?multiverseid=290&type=card",
		"name": "Mountain"
	},
	{
		"id": 290,
		"imageUrl": "http://gatherer.wizards.com/Handlers/Image.ashx?multiverseid=290&type=card",
		"name": "Mountain"
	},
	{
		"id": 290,
		"imageUrl": "http://gatherer.wizards.com/Handlers/Image.ashx?multiverseid=290&type=card",
		"name": "Mountain"
	},
	{
		"id": 290,
		"imageUrl": "http://gatherer.wizards.com/Handlers/Image.ashx?multiverseid=290&type=card",
		"name": "Mountain"
	},
	{
		"id": 290,
		"imageUrl": "http://gatherer.wizards.com/Handlers/Image.ashx?multiverseid=290&type=card",
		"name": "Mountain"
	},
  {
    "id": 368950,
    "imageUrl": "http://gatherer.wizards.com/Handlers/Image.ashx?multiverseid=368950&type=card",
    "name": "Wear"
  },
  {
    "id": 368950,
    "imageUrl": "http://gatherer.wizards.com/Handlers/Image.ashx?multiverseid=368950&type=card",
    "name": "Wear"
  },
  {
    "id": 368950,
    "imageUrl": "http://gatherer.wizards.com/Handlers/Image.ashx?multiverseid=368950&type=card",
    "name": "Wear"
  },
  {
    "id": 368950,
    "imageUrl": "http://gatherer.wizards.com/Handlers/Image.ashx?multiverseid=368950&type=card",
    "name": "Wear"
  }
]